util_rpa/__init__.py
util_rpa/logging_utils.py
util_rpa/mail/__init__.py
util_rpa/mail/_template_utils.py
util_rpa/mail/models.py
util_rpa/mail/notifier.py
util_rpa/mail/notify.py
util_rpa/mail/result.py
util_rpa/mail/smtp.py
util_rpa/mail/smtp_notifier.py
util_rpa/mail/smtp_result.py
util_rpa/mail/template.py
util_rpa/sftp/__init__.py
util_rpa/sftp/exceptions.py
util_rpa/sftp/sftp_client.py
util_rpa/sftp/sftp_credentials.py
util_rpa/sql/__init__.py
util_rpa/sql/bcp.py
util_rpa/sql/parsers.py
util_rpa/sql/sql_credentials.py
util_rpa/sql/sqlcmd.py
util_rpa/sql/utilities.py
util_rpa-2.2.4.dist-info/licenses/LICENSE.txt
util_rpa-2.2.4.dist-info/METADATA
util_rpa-2.2.4.dist-info/WHEEL
util_rpa-2.2.4.dist-info/top_level.txt
util_rpa-2.2.4.dist-info/RECORD
