Metadata-Version: 2.4
Name: util-rpa
Version: 2.2.4
Summary: Utilidades corporativas para automatización RPA en Python
Author-email: Jonathan Bolo <jbolo.des@gmail.com>
License-Expression: MIT
Classifier: Programming Language :: Python :: 3
Classifier: Programming Language :: Python :: 3.9
Classifier: Topic :: Utilities
Requires-Python: <3.13,>=3.9
License-File: LICENSE.txt
Requires-Dist: pandas<3.0,>=2.0
Requires-Dist: python-dateutil<3.0,>=2.8
Provides-Extra: sftp
Requires-Dist: paramiko<4.0,>=3.4; extra == "sftp"
Provides-Extra: dev
Requires-Dist: pytest<9,>=7; extra == "dev"
Requires-Dist: flake8; extra == "dev"
Requires-Dist: flake8-docstrings>=1.6.0; extra == "dev"
Requires-Dist: autopep8>=2.3.2; extra == "dev"
Requires-Dist: mypy>=1.18.2; extra == "dev"
Requires-Dist: twine>=4.0.2; extra == "dev"
Requires-Dist: setuptools>=67.6.1; extra == "dev"
Requires-Dist: python-dotenv>=1.0; extra == "dev"
Dynamic: license-file
